{
  "!" : "com.github.javaparser.ast.CompilationUnit",
  "range" : {
    "beginColumn" : 1,
    "beginLine" : 1,
    "endColumn" : 3,
    "endLine" : 64
  },
  "imports" : [ {
    "!" : "com.github.javaparser.ast.ImportDeclaration",
    "range" : {
      "beginColumn" : 1,
      "beginLine" : 3,
      "endColumn" : 31,
      "endLine" : 3
    },
    "children" : [ {
      "!" : "com.github.javaparser.ast.expr.Name",
      "range" : {
        "beginColumn" : 8,
        "beginLine" : 3,
        "endColumn" : 30,
        "endLine" : 3
      },
      "children" : [ {
        "!" : "com.github.javaparser.ast.expr.Name",
        "range" : {
          "beginColumn" : 8,
          "beginLine" : 3,
          "endColumn" : 22,
          "endLine" : 3
        },
        "children" : [ {
          "!" : "com.github.javaparser.ast.expr.Name",
          "range" : {
            "beginColumn" : 8,
            "beginLine" : 3,
            "endColumn" : 14,
            "endLine" : 3
          }
        } ]
      } ]
    } ]
  }, {
    "!" : "com.github.javaparser.ast.ImportDeclaration",
    "range" : {
      "beginColumn" : 1,
      "beginLine" : 4,
      "endColumn" : 31,
      "endLine" : 4
    },
    "children" : [ {
      "!" : "com.github.javaparser.ast.expr.Name",
      "range" : {
        "beginColumn" : 8,
        "beginLine" : 4,
        "endColumn" : 30,
        "endLine" : 4
      },
      "children" : [ {
        "!" : "com.github.javaparser.ast.expr.Name",
        "range" : {
          "beginColumn" : 8,
          "beginLine" : 4,
          "endColumn" : 23,
          "endLine" : 4
        },
        "children" : [ {
          "!" : "com.github.javaparser.ast.expr.Name",
          "range" : {
            "beginColumn" : 8,
            "beginLine" : 3,
            "endColumn" : 14,
            "endLine" : 3
          }
        } ]
      } ]
    } ]
  }, {
    "!" : "com.github.javaparser.ast.ImportDeclaration",
    "range" : {
      "beginColumn" : 1,
      "beginLine" : 5,
      "endColumn" : 36,
      "endLine" : 5
    },
    "children" : [ {
      "!" : "com.github.javaparser.ast.expr.Name",
      "range" : {
        "beginColumn" : 8,
        "beginLine" : 5,
        "endColumn" : 35,
        "endLine" : 5
      },
      "children" : [ {
        "!" : "com.github.javaparser.ast.expr.Name",
        "range" : {
          "beginColumn" : 8,
          "beginLine" : 4,
          "endColumn" : 23,
          "endLine" : 4
        },
        "children" : [ {
          "!" : "com.github.javaparser.ast.expr.Name",
          "range" : {
            "beginColumn" : 8,
            "beginLine" : 3,
            "endColumn" : 14,
            "endLine" : 3
          }
        } ]
      } ]
    } ]
  }, {
    "!" : "com.github.javaparser.ast.ImportDeclaration",
    "range" : {
      "beginColumn" : 1,
      "beginLine" : 6,
      "endColumn" : 44,
      "endLine" : 6
    },
    "children" : [ {
      "!" : "com.github.javaparser.ast.expr.Name",
      "range" : {
        "beginColumn" : 8,
        "beginLine" : 6,
        "endColumn" : 43,
        "endLine" : 6
      },
      "children" : [ {
        "!" : "com.github.javaparser.ast.expr.Name",
        "range" : {
          "beginColumn" : 8,
          "beginLine" : 4,
          "endColumn" : 23,
          "endLine" : 4
        },
        "children" : [ {
          "!" : "com.github.javaparser.ast.expr.Name",
          "range" : {
            "beginColumn" : 8,
            "beginLine" : 3,
            "endColumn" : 14,
            "endLine" : 3
          }
        } ]
      } ]
    } ]
  }, {
    "!" : "com.github.javaparser.ast.ImportDeclaration",
    "range" : {
      "beginColumn" : 1,
      "beginLine" : 7,
      "endColumn" : 38,
      "endLine" : 7
    },
    "children" : [ {
      "!" : "com.github.javaparser.ast.expr.Name",
      "range" : {
        "beginColumn" : 8,
        "beginLine" : 7,
        "endColumn" : 37,
        "endLine" : 7
      },
      "children" : [ {
        "!" : "com.github.javaparser.ast.expr.Name",
        "range" : {
          "beginColumn" : 8,
          "beginLine" : 4,
          "endColumn" : 23,
          "endLine" : 4
        },
        "children" : [ {
          "!" : "com.github.javaparser.ast.expr.Name",
          "range" : {
            "beginColumn" : 8,
            "beginLine" : 3,
            "endColumn" : 14,
            "endLine" : 3
          }
        } ]
      } ]
    } ]
  }, {
    "!" : "com.github.javaparser.ast.ImportDeclaration",
    "range" : {
      "beginColumn" : 1,
      "beginLine" : 8,
      "endColumn" : 24,
      "endLine" : 8
    },
    "children" : [ {
      "!" : "com.github.javaparser.ast.expr.Name",
      "range" : {
        "beginColumn" : 8,
        "beginLine" : 8,
        "endColumn" : 23,
        "endLine" : 8
      },
      "children" : [ {
        "!" : "com.github.javaparser.ast.expr.Name",
        "range" : {
          "beginColumn" : 8,
          "beginLine" : 8,
          "endColumn" : 19,
          "endLine" : 8
        },
        "children" : [ {
          "!" : "com.github.javaparser.ast.expr.Name",
          "range" : {
            "beginColumn" : 8,
            "beginLine" : 3,
            "endColumn" : 14,
            "endLine" : 3
          }
        } ]
      } ]
    } ]
  }, {
    "!" : "com.github.javaparser.ast.ImportDeclaration",
    "range" : {
      "beginColumn" : 1,
      "beginLine" : 9,
      "endColumn" : 25,
      "endLine" : 9
    },
    "children" : [ {
      "!" : "com.github.javaparser.ast.expr.Name",
      "range" : {
        "beginColumn" : 8,
        "beginLine" : 9,
        "endColumn" : 24,
        "endLine" : 9
      },
      "children" : [ {
        "!" : "com.github.javaparser.ast.expr.Name",
        "range" : {
          "beginColumn" : 8,
          "beginLine" : 9,
          "endColumn" : 16,
          "endLine" : 9
        },
        "children" : [ {
          "!" : "com.github.javaparser.ast.expr.Name",
          "range" : {
            "beginColumn" : 8,
            "beginLine" : 9,
            "endColumn" : 11,
            "endLine" : 9
          }
        } ]
      } ]
    } ]
  }, {
    "!" : "com.github.javaparser.ast.ImportDeclaration",
    "range" : {
      "beginColumn" : 1,
      "beginLine" : 10,
      "endColumn" : 22,
      "endLine" : 10
    },
    "children" : [ {
      "!" : "com.github.javaparser.ast.expr.Name",
      "range" : {
        "beginColumn" : 8,
        "beginLine" : 10,
        "endColumn" : 21,
        "endLine" : 10
      },
      "children" : [ {
        "!" : "com.github.javaparser.ast.expr.Name",
        "range" : {
          "beginColumn" : 8,
          "beginLine" : 9,
          "endColumn" : 16,
          "endLine" : 9
        },
        "children" : [ {
          "!" : "com.github.javaparser.ast.expr.Name",
          "range" : {
            "beginColumn" : 8,
            "beginLine" : 9,
            "endColumn" : 11,
            "endLine" : 9
          }
        } ]
      } ]
    } ]
  }, {
    "!" : "com.github.javaparser.ast.ImportDeclaration",
    "range" : {
      "beginColumn" : 1,
      "beginLine" : 11,
      "endColumn" : 24,
      "endLine" : 11
    },
    "children" : [ {
      "!" : "com.github.javaparser.ast.expr.Name",
      "range" : {
        "beginColumn" : 8,
        "beginLine" : 11,
        "endColumn" : 23,
        "endLine" : 11
      },
      "children" : [ {
        "!" : "com.github.javaparser.ast.expr.Name",
        "range" : {
          "beginColumn" : 8,
          "beginLine" : 9,
          "endColumn" : 16,
          "endLine" : 9
        },
        "children" : [ {
          "!" : "com.github.javaparser.ast.expr.Name",
          "range" : {
            "beginColumn" : 8,
            "beginLine" : 9,
            "endColumn" : 11,
            "endLine" : 9
          }
        } ]
      } ]
    } ]
  }, {
    "!" : "com.github.javaparser.ast.ImportDeclaration",
    "range" : {
      "beginColumn" : 1,
      "beginLine" : 12,
      "endColumn" : 21,
      "endLine" : 12
    },
    "children" : [ {
      "!" : "com.github.javaparser.ast.expr.Name",
      "range" : {
        "beginColumn" : 8,
        "beginLine" : 12,
        "endColumn" : 20,
        "endLine" : 12
      },
      "children" : [ {
        "!" : "com.github.javaparser.ast.expr.Name",
        "range" : {
          "beginColumn" : 8,
          "beginLine" : 9,
          "endColumn" : 16,
          "endLine" : 9
        },
        "children" : [ {
          "!" : "com.github.javaparser.ast.expr.Name",
          "range" : {
            "beginColumn" : 8,
            "beginLine" : 9,
            "endColumn" : 11,
            "endLine" : 9
          }
        } ]
      } ]
    } ]
  } ],
  "types" : [ {
    "!" : "com.github.javaparser.ast.body.ClassOrInterfaceDeclaration",
    "range" : {
      "beginColumn" : 1,
      "beginLine" : 17,
      "endColumn" : 1,
      "endLine" : 64
    },
    "isInterface" : false,
    "extendedTypes" : [ ],
    "implementedTypes" : [ {
      "!" : "com.github.javaparser.ast.type.ClassOrInterfaceType",
      "range" : {
        "beginColumn" : 50,
        "beginLine" : 17,
        "endColumn" : 68,
        "endLine" : 17
      },
      "children" : [ {
        "!" : "com.github.javaparser.ast.expr.SimpleName",
        "range" : {
          "beginColumn" : 50,
          "beginLine" : 17,
          "endColumn" : 68,
          "endLine" : 17
        }
      } ]
    } ],
    "members" : [ { }, { }, { }, {
      "!" : "com.github.javaparser.ast.body.ConstructorDeclaration",
      "range" : {
        "beginColumn" : 3,
        "beginLine" : 25,
        "endColumn" : 3,
        "endLine" : 39
      },
      "children" : [ {
        "!" : "com.github.javaparser.ast.Modifier",
        "range" : {
          "beginColumn" : 3,
          "beginLine" : 25,
          "endColumn" : 8,
          "endLine" : 25
        },
        "modifier" : "public"
      }, {
        "!" : "com.github.javaparser.ast.expr.SimpleName",
        "range" : {
          "beginColumn" : 10,
          "beginLine" : 25,
          "endColumn" : 27,
          "endLine" : 25
        }
      }, {
        "!" : "com.github.javaparser.ast.body.Parameter",
        "range" : {
          "beginColumn" : 29,
          "beginLine" : 25,
          "endColumn" : 43,
          "endLine" : 25
        },
        "children" : [ {
          "!" : "com.github.javaparser.ast.type.ClassOrInterfaceType",
          "range" : {
            "beginColumn" : 29,
            "beginLine" : 25,
            "endColumn" : 35,
            "endLine" : 25
          },
          "children" : [ {
            "!" : "com.github.javaparser.ast.expr.SimpleName",
            "range" : {
              "beginColumn" : 29,
              "beginLine" : 25,
              "endColumn" : 35,
              "endLine" : 25
            }
          } ]
        }, {
          "!" : "com.github.javaparser.ast.expr.SimpleName",
          "range" : {
            "beginColumn" : 37,
            "beginLine" : 25,
            "endColumn" : 43,
            "endLine" : 25
          }
        } ]
      }, {
        "!" : "com.github.javaparser.ast.stmt.BlockStmt",
        "range" : {
          "beginColumn" : 46,
          "beginLine" : 25,
          "endColumn" : 3,
          "endLine" : 39
        },
        "statements" : [ {
          "!" : "com.github.javaparser.ast.stmt.ExpressionStmt",
          "range" : {
            "beginColumn" : 5,
            "beginLine" : 26,
            "endColumn" : 85,
            "endLine" : 26
          },
          "children" : [ {
            "!" : "com.github.javaparser.ast.expr.AssignExpr",
            "range" : {
              "beginColumn" : 5,
              "beginLine" : 26,
              "endColumn" : 84,
              "endLine" : 26
            },
            "children" : [ {
              "!" : "com.github.javaparser.ast.expr.NameExpr",
              "range" : {
                "beginColumn" : 5,
                "beginLine" : 26,
                "endColumn" : 17,
                "endLine" : 26
              },
              "children" : [ {
                "!" : "com.github.javaparser.ast.expr.SimpleName",
                "range" : {
                  "beginColumn" : 5,
                  "beginLine" : 26,
                  "endColumn" : 17,
                  "endLine" : 26
                }
              } ]
            }, {
              "!" : "com.github.javaparser.ast.expr.CastExpr",
              "range" : {
                "beginColumn" : 21,
                "beginLine" : 26,
                "endColumn" : 84,
                "endLine" : 26
              },
              "children" : [ {
                "!" : "com.github.javaparser.ast.type.ClassOrInterfaceType",
                "range" : {
                  "beginColumn" : 22,
                  "beginLine" : 26,
                  "endColumn" : 34,
                  "endLine" : 26
                },
                "children" : [ {
                  "!" : "com.github.javaparser.ast.expr.SimpleName",
                  "range" : {
                    "beginColumn" : 22,
                    "beginLine" : 26,
                    "endColumn" : 34,
                    "endLine" : 26
                  }
                } ]
              }, {
                "!" : "com.github.javaparser.ast.expr.MethodCallExpr",
                "range" : {
                  "beginColumn" : 37,
                  "beginLine" : 26,
                  "endColumn" : 84,
                  "endLine" : 26
                },
                "scope" : {
                  "!" : "com.github.javaparser.ast.expr.NameExpr",
                  "range" : {
                    "beginColumn" : 37,
                    "beginLine" : 26,
                    "endColumn" : 43,
                    "endLine" : 26
                  },
                  "children" : [ {
                    "!" : "com.github.javaparser.ast.expr.SimpleName",
                    "range" : {
                      "beginColumn" : 37,
                      "beginLine" : 25,
                      "endColumn" : 43,
                      "endLine" : 25
                    }
                  } ]
                },
                "name" : {
                  "!" : "com.github.javaparser.ast.expr.SimpleName",
                  "range" : {
                    "beginColumn" : 45,
                    "beginLine" : 26,
                    "endColumn" : 60,
                    "endLine" : 26
                  }
                },
                "arguments" : [ {
                  "!" : "com.github.javaparser.ast.expr.FieldAccessExpr",
                  "range" : {
                    "beginColumn" : 62,
                    "beginLine" : 26,
                    "endColumn" : 83,
                    "endLine" : 26
                  },
                  "scope" : {
                    "!" : "com.github.javaparser.ast.expr.NameExpr",
                    "range" : {
                      "beginColumn" : 62,
                      "beginLine" : 26,
                      "endColumn" : 68,
                      "endLine" : 26
                    },
                    "children" : [ {
                      "!" : "com.github.javaparser.ast.expr.SimpleName",
                      "range" : {
                        "beginColumn" : 29,
                        "beginLine" : 25,
                        "endColumn" : 35,
                        "endLine" : 25
                      }
                    } ]
                  },
                  "name" : {
                    "!" : "com.github.javaparser.ast.expr.SimpleName",
                    "range" : {
                      "beginColumn" : 70,
                      "beginLine" : 26,
                      "endColumn" : 83,
                      "endLine" : 26
                    }
                  }
                } ]
              } ]
            } ]
          } ]
        }, {
          "!" : "com.github.javaparser.ast.stmt.ExpressionStmt",
          "range" : {
            "beginColumn" : 5,
            "beginLine" : 27,
            "endColumn" : 75,
            "endLine" : 27
          },
          "children" : [ {
            "!" : "com.github.javaparser.ast.expr.VariableDeclarationExpr",
            "range" : {
              "beginColumn" : 5,
              "beginLine" : 27,
              "endColumn" : 74,
              "endLine" : 27
            },
            "children" : [ {
              "!" : "com.github.javaparser.ast.body.VariableDeclarator",
              "range" : {
                "beginColumn" : 18,
                "beginLine" : 27,
                "endColumn" : 74,
                "endLine" : 27
              },
              "name" : {
                "!" : "com.github.javaparser.ast.expr.SimpleName",
                "range" : {
                  "beginColumn" : 18,
                  "beginLine" : 27,
                  "endColumn" : 27,
                  "endLine" : 27
                }
              },
              "initializer" : {
                "!" : "com.github.javaparser.ast.expr.MethodCallExpr",
                "range" : {
                  "beginColumn" : 31,
                  "beginLine" : 27,
                  "endColumn" : 74,
                  "endLine" : 27
                },
                "scope" : {
                  "!" : "com.github.javaparser.ast.expr.NameExpr",
                  "range" : {
                    "beginColumn" : 5,
                    "beginLine" : 26,
                    "endColumn" : 17,
                    "endLine" : 26
                  },
                  "children" : [ {
                    "!" : "com.github.javaparser.ast.expr.SimpleName",
                    "range" : {
                      "beginColumn" : 5,
                      "beginLine" : 26,
                      "endColumn" : 17,
                      "endLine" : 26
                    }
                  } ]
                },
                "name" : {
                  "!" : "com.github.javaparser.ast.expr.SimpleName",
                  "range" : {
                    "beginColumn" : 45,
                    "beginLine" : 27,
                    "endColumn" : 57,
                    "endLine" : 27
                  }
                },
                "arguments" : [ {
                  "!" : "com.github.javaparser.ast.expr.FieldAccessExpr",
                  "range" : {
                    "beginColumn" : 59,
                    "beginLine" : 27,
                    "endColumn" : 73,
                    "endLine" : 27
                  },
                  "scope" : {
                    "!" : "com.github.javaparser.ast.expr.NameExpr",
                    "range" : {
                      "beginColumn" : 59,
                      "beginLine" : 27,
                      "endColumn" : 64,
                      "endLine" : 27
                    },
                    "children" : [ {
                      "!" : "com.github.javaparser.ast.expr.SimpleName",
                      "range" : {
                        "beginColumn" : 59,
                        "beginLine" : 27,
                        "endColumn" : 64,
                        "endLine" : 27
                      }
                    } ]
                  },
                  "name" : {
                    "!" : "com.github.javaparser.ast.expr.SimpleName",
                    "range" : {
                      "beginColumn" : 66,
                      "beginLine" : 27,
                      "endColumn" : 73,
                      "endLine" : 27
                    }
                  }
                } ]
              }
            } ]
          } ]
        }, {
          "!" : "com.github.javaparser.ast.stmt.ForEachStmt",
          "range" : {
            "beginColumn" : 5,
            "beginLine" : 28,
            "endColumn" : 5,
            "endLine" : 38
          },
          "children" : [ {
            "!" : "com.github.javaparser.ast.expr.VariableDeclarationExpr",
            "range" : {
              "beginColumn" : 10,
              "beginLine" : 28,
              "endColumn" : 22,
              "endLine" : 28
            },
            "children" : [ {
              "!" : "com.github.javaparser.ast.body.VariableDeclarator",
              "range" : {
                "beginColumn" : 17,
                "beginLine" : 28,
                "endColumn" : 22,
                "endLine" : 28
              },
              "name" : {
                "!" : "com.github.javaparser.ast.expr.SimpleName",
                "range" : {
                  "beginColumn" : 17,
                  "beginLine" : 28,
                  "endColumn" : 22,
                  "endLine" : 28
                }
              }
            } ]
          }, {
            "!" : "com.github.javaparser.ast.expr.NameExpr",
            "range" : {
              "beginColumn" : 26,
              "beginLine" : 28,
              "endColumn" : 35,
              "endLine" : 28
            },
            "children" : [ {
              "!" : "com.github.javaparser.ast.expr.SimpleName",
              "range" : {
                "beginColumn" : 18,
                "beginLine" : 27,
                "endColumn" : 27,
                "endLine" : 27
              }
            } ]
          }, {
            "!" : "com.github.javaparser.ast.stmt.BlockStmt",
            "range" : {
              "beginColumn" : 38,
              "beginLine" : 28,
              "endColumn" : 5,
              "endLine" : 38
            },
            "statements" : [ {
              "!" : "com.github.javaparser.ast.stmt.IfStmt",
              "range" : {
                "beginColumn" : 7,
                "beginLine" : 34,
                "endColumn" : 7,
                "endLine" : 37
              },
              "condition" : {
                "!" : "com.github.javaparser.ast.expr.MethodCallExpr",
                "range" : {
                  "beginColumn" : 11,
                  "beginLine" : 34,
                  "endColumn" : 64,
                  "endLine" : 34
                },
                "scope" : {
                  "!" : "com.github.javaparser.ast.expr.MethodCallExpr",
                  "range" : {
                    "beginColumn" : 11,
                    "beginLine" : 34,
                    "endColumn" : 40,
                    "endLine" : 34
                  },
                  "scope" : {
                    "!" : "com.github.javaparser.ast.expr.MethodCallExpr",
                    "range" : {
                      "beginColumn" : 11,
                      "beginLine" : 34,
                      "endColumn" : 26,
                      "endLine" : 34
                    },
                    "scope" : {
                      "!" : "com.github.javaparser.ast.expr.NameExpr",
                      "range" : {
                        "beginColumn" : 11,
                        "beginLine" : 34,
                        "endColumn" : 16,
                        "endLine" : 34
                      },
                      "children" : [ {
                        "!" : "com.github.javaparser.ast.expr.SimpleName",
                        "range" : {
                          "beginColumn" : 17,
                          "beginLine" : 28,
                          "endColumn" : 22,
                          "endLine" : 28
                        }
                      } ]
                    },
                    "name" : {
                      "!" : "com.github.javaparser.ast.expr.SimpleName",
                      "range" : {
                        "beginColumn" : 18,
                        "beginLine" : 34,
                        "endColumn" : 24,
                        "endLine" : 34
                      }
                    },
                    "arguments" : [ ]
                  },
                  "name" : {
                    "!" : "com.github.javaparser.ast.expr.SimpleName",
                    "range" : {
                      "beginColumn" : 28,
                      "beginLine" : 34,
                      "endColumn" : 38,
                      "endLine" : 34
                    }
                  },
                  "arguments" : [ ]
                },
                "name" : {
                  "!" : "com.github.javaparser.ast.expr.SimpleName",
                  "range" : {
                    "beginColumn" : 42,
                    "beginLine" : 34,
                    "endColumn" : 49,
                    "endLine" : 34
                  }
                },
                "arguments" : [ {
                  "!" : "com.github.javaparser.ast.expr.StringLiteralExpr",
                  "range" : {
                    "beginColumn" : 51,
                    "beginLine" : 34,
                    "endColumn" : 63,
                    "endLine" : 34
                  }
                } ]
              },
              "thenStmt" : {
                "!" : "com.github.javaparser.ast.stmt.BlockStmt",
                "range" : {
                  "beginColumn" : 67,
                  "beginLine" : 34,
                  "endColumn" : 7,
                  "endLine" : 37
                },
                "statements" : [ {
                  "!" : "com.github.javaparser.ast.stmt.ExpressionStmt",
                  "range" : {
                    "beginColumn" : 9,
                    "beginLine" : 35,
                    "endColumn" : 88,
                    "endLine" : 35
                  },
                  "children" : [ {
                    "!" : "com.github.javaparser.ast.expr.MethodCallExpr",
                    "range" : {
                      "beginColumn" : 9,
                      "beginLine" : 35,
                      "endColumn" : 87,
                      "endLine" : 35
                    },
                    "scope" : {
                      "!" : "com.github.javaparser.ast.expr.NameExpr",
                      "range" : {
                        "beginColumn" : 5,
                        "beginLine" : 26,
                        "endColumn" : 17,
                        "endLine" : 26
                      },
                      "children" : [ {
                        "!" : "com.github.javaparser.ast.expr.SimpleName",
                        "range" : {
                          "beginColumn" : 5,
                          "beginLine" : 26,
                          "endColumn" : 17,
                          "endLine" : 26
                        }
                      } ]
                    },
                    "name" : {
                      "!" : "com.github.javaparser.ast.expr.SimpleName",
                      "range" : {
                        "beginColumn" : 23,
                        "beginLine" : 35,
                        "endColumn" : 38,
                        "endLine" : 35
                      }
                    },
                    "arguments" : [ {
                      "!" : "com.github.javaparser.ast.expr.ThisExpr",
                      "range" : {
                        "beginColumn" : 40,
                        "beginLine" : 35,
                        "endColumn" : 43,
                        "endLine" : 35
                      }
                    }, {
                      "!" : "com.github.javaparser.ast.expr.NameExpr",
                      "range" : {
                        "beginColumn" : 11,
                        "beginLine" : 34,
                        "endColumn" : 16,
                        "endLine" : 34
                      },
                      "children" : [ {
                        "!" : "com.github.javaparser.ast.expr.SimpleName",
                        "range" : {
                          "beginColumn" : 17,
                          "beginLine" : 28,
                          "endColumn" : 22,
                          "endLine" : 28
                        }
                      } ]
                    }, {
                      "!" : "com.github.javaparser.ast.expr.FieldAccessExpr",
                      "range" : {
                        "beginColumn" : 54,
                        "beginLine" : 35,
                        "endColumn" : 86,
                        "endLine" : 35
                      },
                      "scope" : {
                        "!" : "com.github.javaparser.ast.expr.NameExpr",
                        "range" : {
                          "beginColumn" : 54,
                          "beginLine" : 35,
                          "endColumn" : 66,
                          "endLine" : 35
                        },
                        "children" : [ {
                          "!" : "com.github.javaparser.ast.expr.SimpleName",
                          "range" : {
                            "beginColumn" : 22,
                            "beginLine" : 26,
                            "endColumn" : 34,
                            "endLine" : 26
                          }
                        } ]
                      },
                      "name" : {
                        "!" : "com.github.javaparser.ast.expr.SimpleName",
                        "range" : {
                          "beginColumn" : 68,
                          "beginLine" : 35,
                          "endColumn" : 86,
                          "endLine" : 35
                        }
                      }
                    } ]
                  } ]
                } ]
              }
            } ]
          } ]
        } ]
      } ]
    }, {
      "!" : "com.github.javaparser.ast.body.MethodDeclaration",
      "range" : {
        "beginColumn" : 3,
        "beginLine" : 41,
        "endColumn" : 3,
        "endLine" : 43
      },
      "modifiers" : [ {
        "!" : "com.github.javaparser.ast.Modifier",
        "range" : {
          "beginColumn" : 3,
          "beginLine" : 25,
          "endColumn" : 8,
          "endLine" : 25
        },
        "modifier" : "public"
      } ],
      "parameters" : [ ],
      "type" : {
        "!" : "com.github.javaparser.ast.type.VoidType",
        "range" : {
          "beginColumn" : 10,
          "beginLine" : 41,
          "endColumn" : 13,
          "endLine" : 41
        }
      },
      "body" : {
        "!" : "com.github.javaparser.ast.stmt.BlockStmt",
        "range" : {
          "beginColumn" : 22,
          "beginLine" : 41,
          "endColumn" : 3,
          "endLine" : 43
        },
        "statements" : [ {
          "!" : "com.github.javaparser.ast.stmt.ExpressionStmt",
          "range" : {
            "beginColumn" : 5,
            "beginLine" : 42,
            "endColumn" : 43,
            "endLine" : 42
          },
          "children" : [ {
            "!" : "com.github.javaparser.ast.expr.MethodCallExpr",
            "range" : {
              "beginColumn" : 5,
              "beginLine" : 42,
              "endColumn" : 42,
              "endLine" : 42
            },
            "scope" : {
              "!" : "com.github.javaparser.ast.expr.NameExpr",
              "range" : {
                "beginColumn" : 5,
                "beginLine" : 26,
                "endColumn" : 17,
                "endLine" : 26
              },
              "children" : [ {
                "!" : "com.github.javaparser.ast.expr.SimpleName",
                "range" : {
                  "beginColumn" : 5,
                  "beginLine" : 26,
                  "endColumn" : 17,
                  "endLine" : 26
                }
              } ]
            },
            "name" : {
              "!" : "com.github.javaparser.ast.expr.SimpleName",
              "range" : {
                "beginColumn" : 19,
                "beginLine" : 42,
                "endColumn" : 36,
                "endLine" : 42
              }
            },
            "arguments" : [ {
              "!" : "com.github.javaparser.ast.expr.ThisExpr",
              "range" : {
                "beginColumn" : 40,
                "beginLine" : 35,
                "endColumn" : 43,
                "endLine" : 35
              }
            } ]
          } ]
        } ]
      }
    }, {
      "!" : "com.github.javaparser.ast.body.MethodDeclaration",
      "range" : {
        "beginColumn" : 3,
        "beginLine" : 45,
        "endColumn" : 3,
        "endLine" : 55
      },
      "modifiers" : [ {
        "!" : "com.github.javaparser.ast.Modifier",
        "range" : {
          "beginColumn" : 3,
          "beginLine" : 25,
          "endColumn" : 8,
          "endLine" : 25
        },
        "modifier" : "public"
      } ],
      "parameters" : [ ],
      "type" : {
        "!" : "com.github.javaparser.ast.type.VoidType",
        "range" : {
          "beginColumn" : 10,
          "beginLine" : 41,
          "endColumn" : 13,
          "endLine" : 41
        }
      },
      "body" : {
        "!" : "com.github.javaparser.ast.stmt.BlockStmt",
        "range" : {
          "beginColumn" : 32,
          "beginLine" : 45,
          "endColumn" : 3,
          "endLine" : 55
        },
        "statements" : [ {
          "!" : "com.github.javaparser.ast.stmt.ForEachStmt",
          "range" : {
            "beginColumn" : 5,
            "beginLine" : 46,
            "endColumn" : 5,
            "endLine" : 54
          },
          "children" : [ {
            "!" : "com.github.javaparser.ast.expr.VariableDeclarationExpr",
            "range" : {
              "beginColumn" : 10,
              "beginLine" : 46,
              "endColumn" : 39,
              "endLine" : 46
            },
            "children" : [ {
              "!" : "com.github.javaparser.ast.body.VariableDeclarator",
              "range" : {
                "beginColumn" : 35,
                "beginLine" : 46,
                "endColumn" : 39,
                "endLine" : 46
              },
              "name" : {
                "!" : "com.github.javaparser.ast.expr.SimpleName",
                "range" : {
                  "beginColumn" : 35,
                  "beginLine" : 46,
                  "endColumn" : 39,
                  "endLine" : 46
                }
              }
            } ]
          }, {
            "!" : "com.github.javaparser.ast.expr.MethodCallExpr",
            "range" : {
              "beginColumn" : 43,
              "beginLine" : 46,
              "endColumn" : 74,
              "endLine" : 46
            },
            "scope" : {
              "!" : "com.github.javaparser.ast.expr.NameExpr",
              "range" : {
                "beginColumn" : 43,
                "beginLine" : 46,
                "endColumn" : 63,
                "endLine" : 46
              },
              "children" : [ {
                "!" : "com.github.javaparser.ast.expr.SimpleName",
                "range" : {
                  "beginColumn" : 43,
                  "beginLine" : 46,
                  "endColumn" : 63,
                  "endLine" : 46
                }
              } ]
            },
            "name" : {
              "!" : "com.github.javaparser.ast.expr.SimpleName",
              "range" : {
                "beginColumn" : 65,
                "beginLine" : 46,
                "endColumn" : 72,
                "endLine" : 46
              }
            },
            "arguments" : [ ]
          }, {
            "!" : "com.github.javaparser.ast.stmt.BlockStmt",
            "range" : {
              "beginColumn" : 77,
              "beginLine" : 46,
              "endColumn" : 5,
              "endLine" : 54
            },
            "statements" : [ {
              "!" : "com.github.javaparser.ast.stmt.ExpressionStmt",
              "range" : {
                "beginColumn" : 7,
                "beginLine" : 47,
                "endColumn" : 37,
                "endLine" : 47
              },
              "children" : [ {
                "!" : "com.github.javaparser.ast.expr.VariableDeclarationExpr",
                "range" : {
                  "beginColumn" : 7,
                  "beginLine" : 47,
                  "endColumn" : 36,
                  "endLine" : 47
                },
                "children" : [ {
                  "!" : "com.github.javaparser.ast.body.VariableDeclarator",
                  "range" : {
                    "beginColumn" : 13,
                    "beginLine" : 47,
                    "endColumn" : 36,
                    "endLine" : 47
                  },
                  "name" : {
                    "!" : "com.github.javaparser.ast.expr.SimpleName",
                    "range" : {
                      "beginColumn" : 13,
                      "beginLine" : 47,
                      "endColumn" : 17,
                      "endLine" : 47
                    }
                  },
                  "initializer" : {
                    "!" : "com.github.javaparser.ast.expr.MethodCallExpr",
                    "range" : {
                      "beginColumn" : 21,
                      "beginLine" : 47,
                      "endColumn" : 36,
                      "endLine" : 47
                    },
                    "scope" : {
                      "!" : "com.github.javaparser.ast.expr.NameExpr",
                      "range" : {
                        "beginColumn" : 21,
                        "beginLine" : 47,
                        "endColumn" : 25,
                        "endLine" : 47
                      },
                      "children" : [ {
                        "!" : "com.github.javaparser.ast.expr.SimpleName",
                        "range" : {
                          "beginColumn" : 35,
                          "beginLine" : 46,
                          "endColumn" : 39,
                          "endLine" : 46
                        }
                      } ]
                    },
                    "name" : {
                      "!" : "com.github.javaparser.ast.expr.SimpleName",
                      "range" : {
                        "beginColumn" : 27,
                        "beginLine" : 47,
                        "endColumn" : 34,
                        "endLine" : 47
                      }
                    },
                    "arguments" : [ ]
                  }
                } ]
              } ]
            }, {
              "!" : "com.github.javaparser.ast.stmt.IfStmt",
              "range" : {
                "beginColumn" : 7,
                "beginLine" : 49,
                "endColumn" : 7,
                "endLine" : 51
              },
              "condition" : {
                "!" : "com.github.javaparser.ast.expr.BinaryExpr",
                "range" : {
                  "beginColumn" : 11,
                  "beginLine" : 49,
                  "endColumn" : 19,
                  "endLine" : 49
                },
                "children" : [ {
                  "!" : "com.github.javaparser.ast.expr.NameExpr",
                  "range" : {
                    "beginColumn" : 11,
                    "beginLine" : 49,
                    "endColumn" : 15,
                    "endLine" : 49
                  },
                  "children" : [ {
                    "!" : "com.github.javaparser.ast.expr.SimpleName",
                    "range" : {
                      "beginColumn" : 13,
                      "beginLine" : 47,
                      "endColumn" : 17,
                      "endLine" : 47
                    }
                  } ]
                }, {
                  "!" : "com.github.javaparser.ast.expr.IntegerLiteralExpr",
                  "range" : {
                    "beginColumn" : 19,
                    "beginLine" : 49,
                    "endColumn" : 19,
                    "endLine" : 49
                  }
                } ]
              },
              "thenStmt" : {
                "!" : "com.github.javaparser.ast.stmt.BlockStmt",
                "range" : {
                  "beginColumn" : 22,
                  "beginLine" : 49,
                  "endColumn" : 7,
                  "endLine" : 51
                },
                "statements" : [ {
                  "!" : "com.github.javaparser.ast.stmt.ContinueStmt",
                  "range" : {
                    "beginColumn" : 9,
                    "beginLine" : 50,
                    "endColumn" : 17,
                    "endLine" : 50
                  }
                } ]
              }
            }, {
              "!" : "com.github.javaparser.ast.stmt.ExpressionStmt",
              "range" : {
                "beginColumn" : 7,
                "beginLine" : 52,
                "endColumn" : 39,
                "endLine" : 52
              },
              "children" : [ {
                "!" : "com.github.javaparser.ast.expr.VariableDeclarationExpr",
                "range" : {
                  "beginColumn" : 7,
                  "beginLine" : 52,
                  "endColumn" : 38,
                  "endLine" : 52
                },
                "children" : [ {
                  "!" : "com.github.javaparser.ast.body.VariableDeclarator",
                  "range" : {
                    "beginColumn" : 13,
                    "beginLine" : 52,
                    "endColumn" : 38,
                    "endLine" : 52
                  },
                  "name" : {
                    "!" : "com.github.javaparser.ast.expr.SimpleName",
                    "range" : {
                      "beginColumn" : 13,
                      "beginLine" : 52,
                      "endColumn" : 17,
                      "endLine" : 52
                    }
                  },
                  "initializer" : {
                    "!" : "com.github.javaparser.ast.expr.BinaryExpr",
                    "range" : {
                      "beginColumn" : 21,
                      "beginLine" : 52,
                      "endColumn" : 38,
                      "endLine" : 52
                    },
                    "children" : [ {
                      "!" : "com.github.javaparser.ast.expr.BinaryExpr",
                      "range" : {
                        "beginColumn" : 21,
                        "beginLine" : 52,
                        "endColumn" : 32,
                        "endLine" : 52
                      },
                      "children" : [ {
                        "!" : "com.github.javaparser.ast.expr.NameExpr",
                        "range" : {
                          "beginColumn" : 11,
                          "beginLine" : 49,
                          "endColumn" : 15,
                          "endLine" : 49
                        },
                        "children" : [ {
                          "!" : "com.github.javaparser.ast.expr.SimpleName",
                          "range" : {
                            "beginColumn" : 13,
                            "beginLine" : 47,
                            "endColumn" : 17,
                            "endLine" : 47
                          }
                        } ]
                      }, {
                        "!" : "com.github.javaparser.ast.expr.DoubleLiteralExpr",
                        "range" : {
                          "beginColumn" : 29,
                          "beginLine" : 52,
                          "endColumn" : 32,
                          "endLine" : 52
                        }
                      } ]
                    }, {
                      "!" : "com.github.javaparser.ast.expr.DoubleLiteralExpr",
                      "range" : {
                        "beginColumn" : 36,
                        "beginLine" : 52,
                        "endColumn" : 38,
                        "endLine" : 52
                      }
                    } ]
                  }
                } ]
              } ]
            }, {
              "!" : "com.github.javaparser.ast.stmt.ExpressionStmt",
              "range" : {
                "beginColumn" : 7,
                "beginLine" : 53,
                "endColumn" : 94,
                "endLine" : 53
              },
              "children" : [ {
                "!" : "com.github.javaparser.ast.expr.MethodCallExpr",
                "range" : {
                  "beginColumn" : 7,
                  "beginLine" : 53,
                  "endColumn" : 93,
                  "endLine" : 53
                },
                "scope" : {
                  "!" : "com.github.javaparser.ast.expr.NameExpr",
                  "range" : {
                    "beginColumn" : 7,
                    "beginLine" : 53,
                    "endColumn" : 9,
                    "endLine" : 53
                  },
                  "children" : [ {
                    "!" : "com.github.javaparser.ast.expr.SimpleName",
                    "range" : {
                      "beginColumn" : 7,
                      "beginLine" : 53,
                      "endColumn" : 9,
                      "endLine" : 53
                    }
                  } ]
                },
                "name" : {
                  "!" : "com.github.javaparser.ast.expr.SimpleName",
                  "range" : {
                    "beginColumn" : 11,
                    "beginLine" : 53,
                    "endColumn" : 11,
                    "endLine" : 53
                  }
                },
                "arguments" : [ {
                  "!" : "com.github.javaparser.ast.expr.NameExpr",
                  "range" : {
                    "beginColumn" : 13,
                    "beginLine" : 53,
                    "endColumn" : 15,
                    "endLine" : 53
                  },
                  "children" : [ {
                    "!" : "com.github.javaparser.ast.expr.SimpleName",
                    "range" : {
                      "beginColumn" : 13,
                      "beginLine" : 53,
                      "endColumn" : 15,
                      "endLine" : 53
                    }
                  } ]
                }, {
                  "!" : "com.github.javaparser.ast.expr.MethodCallExpr",
                  "range" : {
                    "beginColumn" : 18,
                    "beginLine" : 53,
                    "endColumn" : 92,
                    "endLine" : 53
                  },
                  "scope" : {
                    "!" : "com.github.javaparser.ast.expr.NameExpr",
                    "range" : {
                      "beginColumn" : 18,
                      "beginLine" : 53,
                      "endColumn" : 23,
                      "endLine" : 53
                    },
                    "children" : [ {
                      "!" : "com.github.javaparser.ast.expr.SimpleName",
                      "range" : {
                        "beginColumn" : 18,
                        "beginLine" : 53,
                        "endColumn" : 23,
                        "endLine" : 53
                      }
                    } ]
                  },
                  "name" : {
                    "!" : "com.github.javaparser.ast.expr.SimpleName",
                    "range" : {
                      "beginColumn" : 25,
                      "beginLine" : 53,
                      "endColumn" : 30,
                      "endLine" : 53
                    }
                  },
                  "arguments" : [ {
                    "!" : "com.github.javaparser.ast.expr.FieldAccessExpr",
                    "range" : {
                      "beginColumn" : 32,
                      "beginLine" : 53,
                      "endColumn" : 40,
                      "endLine" : 53
                    },
                    "scope" : {
                      "!" : "com.github.javaparser.ast.expr.NameExpr",
                      "range" : {
                        "beginColumn" : 32,
                        "beginLine" : 53,
                        "endColumn" : 37,
                        "endLine" : 53
                      },
                      "children" : [ {
                        "!" : "com.github.javaparser.ast.expr.SimpleName",
                        "range" : {
                          "beginColumn" : 32,
                          "beginLine" : 53,
                          "endColumn" : 37,
                          "endLine" : 53
                        }
                      } ]
                    },
                    "name" : {
                      "!" : "com.github.javaparser.ast.expr.SimpleName",
                      "range" : {
                        "beginColumn" : 39,
                        "beginLine" : 53,
                        "endColumn" : 40,
                        "endLine" : 53
                      }
                    }
                  }, {
                    "!" : "com.github.javaparser.ast.expr.StringLiteralExpr",
                    "range" : {
                      "beginColumn" : 43,
                      "beginLine" : 53,
                      "endColumn" : 61,
                      "endLine" : 53
                    }
                  }, {
                    "!" : "com.github.javaparser.ast.expr.MethodCallExpr",
                    "range" : {
                      "beginColumn" : 64,
                      "beginLine" : 53,
                      "endColumn" : 77,
                      "endLine" : 53
                    },
                    "scope" : {
                      "!" : "com.github.javaparser.ast.expr.NameExpr",
                      "range" : {
                        "beginColumn" : 21,
                        "beginLine" : 47,
                        "endColumn" : 25,
                        "endLine" : 47
                      },
                      "children" : [ {
                        "!" : "com.github.javaparser.ast.expr.SimpleName",
                        "range" : {
                          "beginColumn" : 35,
                          "beginLine" : 46,
                          "endColumn" : 39,
                          "endLine" : 46
                        }
                      } ]
                    },
                    "name" : {
                      "!" : "com.github.javaparser.ast.expr.SimpleName",
                      "range" : {
                        "beginColumn" : 70,
                        "beginLine" : 53,
                        "endColumn" : 75,
                        "endLine" : 53
                      }
                    },
                    "arguments" : [ ]
                  }, {
                    "!" : "com.github.javaparser.ast.expr.NameExpr",
                    "range" : {
                      "beginColumn" : 11,
                      "beginLine" : 49,
                      "endColumn" : 15,
                      "endLine" : 49
                    },
                    "children" : [ {
                      "!" : "com.github.javaparser.ast.expr.SimpleName",
                      "range" : {
                        "beginColumn" : 13,
                        "beginLine" : 47,
                        "endColumn" : 17,
                        "endLine" : 47
                      }
                    } ]
                  }, {
                    "!" : "com.github.javaparser.ast.expr.NameExpr",
                    "range" : {
                      "beginColumn" : 87,
                      "beginLine" : 53,
                      "endColumn" : 91,
                      "endLine" : 53
                    },
                    "children" : [ {
                      "!" : "com.github.javaparser.ast.expr.SimpleName",
                      "range" : {
                        "beginColumn" : 13,
                        "beginLine" : 52,
                        "endColumn" : 17,
                        "endLine" : 52
                      }
                    } ]
                  } ]
                } ]
              } ]
            } ]
          } ]
        } ]
      }
    }, {
      "!" : "com.github.javaparser.ast.body.MethodDeclaration",
      "range" : {
        "beginColumn" : 3,
        "beginLine" : 57,
        "endColumn" : 63,
        "endLine" : 58
      },
      "modifiers" : [ {
        "!" : "com.github.javaparser.ast.Modifier",
        "range" : {
          "beginColumn" : 3,
          "beginLine" : 25,
          "endColumn" : 8,
          "endLine" : 25
        },
        "modifier" : "public"
      } ],
      "parameters" : [ {
        "!" : "com.github.javaparser.ast.body.Parameter",
        "range" : {
          "beginColumn" : 33,
          "beginLine" : 58,
          "endColumn" : 45,
          "endLine" : 58
        },
        "children" : [ {
          "!" : "com.github.javaparser.ast.type.ClassOrInterfaceType",
          "range" : {
            "beginColumn" : 33,
            "beginLine" : 58,
            "endColumn" : 38,
            "endLine" : 58
          },
          "children" : [ {
            "!" : "com.github.javaparser.ast.expr.SimpleName",
            "range" : {
              "beginColumn" : 59,
              "beginLine" : 27,
              "endColumn" : 64,
              "endLine" : 27
            }
          } ]
        }, {
          "!" : "com.github.javaparser.ast.expr.SimpleName",
          "range" : {
            "beginColumn" : 17,
            "beginLine" : 28,
            "endColumn" : 22,
            "endLine" : 28
          }
        } ]
      }, {
        "!" : "com.github.javaparser.ast.body.Parameter",
        "range" : {
          "beginColumn" : 48,
          "beginLine" : 58,
          "endColumn" : 59,
          "endLine" : 58
        },
        "children" : [ {
          "!" : "com.github.javaparser.ast.type.PrimitiveType",
          "range" : {
            "beginColumn" : 48,
            "beginLine" : 58,
            "endColumn" : 50,
            "endLine" : 58
          },
          "type" : "INT"
        }, {
          "!" : "com.github.javaparser.ast.expr.SimpleName",
          "range" : {
            "beginColumn" : 52,
            "beginLine" : 58,
            "endColumn" : 59,
            "endLine" : 58
          }
        } ]
      } ],
      "type" : {
        "!" : "com.github.javaparser.ast.type.VoidType",
        "range" : {
          "beginColumn" : 10,
          "beginLine" : 41,
          "endColumn" : 13,
          "endLine" : 41
        }
      },
      "body" : {
        "!" : "com.github.javaparser.ast.stmt.BlockStmt",
        "range" : {
          "beginColumn" : 62,
          "beginLine" : 58,
          "endColumn" : 63,
          "endLine" : 58
        },
        "statements" : [ ]
      }
    }, {
      "!" : "com.github.javaparser.ast.body.MethodDeclaration",
      "range" : {
        "beginColumn" : 3,
        "beginLine" : 60,
        "endColumn" : 3,
        "endLine" : 63
      },
      "modifiers" : [ {
        "!" : "com.github.javaparser.ast.Modifier",
        "range" : {
          "beginColumn" : 3,
          "beginLine" : 25,
          "endColumn" : 8,
          "endLine" : 25
        },
        "modifier" : "public"
      } ],
      "parameters" : [ {
        "!" : "com.github.javaparser.ast.body.Parameter",
        "range" : {
          "beginColumn" : 31,
          "beginLine" : 61,
          "endColumn" : 53,
          "endLine" : 61
        },
        "children" : [ {
          "!" : "com.github.javaparser.ast.type.ClassOrInterfaceType",
          "range" : {
            "beginColumn" : 31,
            "beginLine" : 61,
            "endColumn" : 41,
            "endLine" : 61
          },
          "children" : [ {
            "!" : "com.github.javaparser.ast.expr.SimpleName",
            "range" : {
              "beginColumn" : 31,
              "beginLine" : 61,
              "endColumn" : 41,
              "endLine" : 61
            }
          } ]
        }, {
          "!" : "com.github.javaparser.ast.expr.SimpleName",
          "range" : {
            "beginColumn" : 43,
            "beginLine" : 61,
            "endColumn" : 53,
            "endLine" : 61
          }
        } ]
      } ],
      "type" : {
        "!" : "com.github.javaparser.ast.type.VoidType",
        "range" : {
          "beginColumn" : 10,
          "beginLine" : 41,
          "endColumn" : 13,
          "endLine" : 41
        }
      },
      "body" : {
        "!" : "com.github.javaparser.ast.stmt.BlockStmt",
        "range" : {
          "beginColumn" : 56,
          "beginLine" : 61,
          "endColumn" : 3,
          "endLine" : 63
        },
        "statements" : [ {
          "!" : "com.github.javaparser.ast.stmt.ExpressionStmt",
          "range" : {
            "beginColumn" : 5,
            "beginLine" : 62,
            "endColumn" : 83,
            "endLine" : 62
          },
          "children" : [ {
            "!" : "com.github.javaparser.ast.expr.MethodCallExpr",
            "range" : {
              "beginColumn" : 5,
              "beginLine" : 62,
              "endColumn" : 82,
              "endLine" : 62
            },
            "scope" : {
              "!" : "com.github.javaparser.ast.expr.NameExpr",
              "range" : {
                "beginColumn" : 43,
                "beginLine" : 46,
                "endColumn" : 63,
                "endLine" : 46
              },
              "children" : [ {
                "!" : "com.github.javaparser.ast.expr.SimpleName",
                "range" : {
                  "beginColumn" : 43,
                  "beginLine" : 46,
                  "endColumn" : 63,
                  "endLine" : 46
                }
              } ]
            },
            "name" : {
              "!" : "com.github.javaparser.ast.expr.SimpleName",
              "range" : {
                "beginColumn" : 27,
                "beginLine" : 62,
                "endColumn" : 29,
                "endLine" : 62
              }
            },
            "arguments" : [ {
              "!" : "com.github.javaparser.ast.expr.MethodCallExpr",
              "range" : {
                "beginColumn" : 31,
                "beginLine" : 62,
                "endColumn" : 58,
                "endLine" : 62
              },
              "scope" : {
                "!" : "com.github.javaparser.ast.expr.FieldAccessExpr",
                "range" : {
                  "beginColumn" : 31,
                  "beginLine" : 62,
                  "endColumn" : 48,
                  "endLine" : 62
                },
                "scope" : {
                  "!" : "com.github.javaparser.ast.expr.NameExpr",
                  "range" : {
                    "beginColumn" : 31,
                    "beginLine" : 62,
                    "endColumn" : 41,
                    "endLine" : 62
                  },
                  "children" : [ {
                    "!" : "com.github.javaparser.ast.expr.SimpleName",
                    "range" : {
                      "beginColumn" : 43,
                      "beginLine" : 61,
                      "endColumn" : 53,
                      "endLine" : 61
                    }
                  } ]
                },
                "name" : {
                  "!" : "com.github.javaparser.ast.expr.SimpleName",
                  "range" : {
                    "beginColumn" : 17,
                    "beginLine" : 28,
                    "endColumn" : 22,
                    "endLine" : 28
                  }
                }
              },
              "name" : {
                "!" : "com.github.javaparser.ast.expr.SimpleName",
                "range" : {
                  "beginColumn" : 18,
                  "beginLine" : 34,
                  "endColumn" : 24,
                  "endLine" : 34
                }
              },
              "arguments" : [ ]
            }, {
              "!" : "com.github.javaparser.ast.expr.ArrayAccessExpr",
              "range" : {
                "beginColumn" : 61,
                "beginLine" : 62,
                "endColumn" : 81,
                "endLine" : 62
              },
              "children" : [ {
                "!" : "com.github.javaparser.ast.expr.FieldAccessExpr",
                "range" : {
                  "beginColumn" : 61,
                  "beginLine" : 62,
                  "endColumn" : 78,
                  "endLine" : 62
                },
                "scope" : {
                  "!" : "com.github.javaparser.ast.expr.NameExpr",
                  "range" : {
                    "beginColumn" : 31,
                    "beginLine" : 62,
                    "endColumn" : 41,
                    "endLine" : 62
                  },
                  "children" : [ {
                    "!" : "com.github.javaparser.ast.expr.SimpleName",
                    "range" : {
                      "beginColumn" : 43,
                      "beginLine" : 61,
                      "endColumn" : 53,
                      "endLine" : 61
                    }
                  } ]
                },
                "name" : {
                  "!" : "com.github.javaparser.ast.expr.SimpleName",
                  "range" : {
                    "beginColumn" : 73,
                    "beginLine" : 62,
                    "endColumn" : 78,
                    "endLine" : 62
                  }
                }
              }, {
                "!" : "com.github.javaparser.ast.expr.IntegerLiteralExpr",
                "range" : {
                  "beginColumn" : 19,
                  "beginLine" : 49,
                  "endColumn" : 19,
                  "endLine" : 49
                }
              } ]
            } ]
          } ]
        } ]
      }
    } ]
  } ]
}